setup.py
ane/__init__.py
ane.egg-info/PKG-INFO
ane.egg-info/SOURCES.txt
ane.egg-info/dependency_links.txt
ane.egg-info/requires.txt
ane.egg-info/top_level.txt