Metadata-Version: 2.1
Name: ane
Version: 1.0.0
Summary: ANE driver interface
Author: Eileen Yoon
Author-email: eyn@gmx.com
